Metadata-Version: 2.1
Name: reorder_python_imports
Version: 3.16.0
Summary: Tool for reordering python imports
Home-page: https://github.com/asottile/reorder-python-imports
Author: Anthony Sottile
Author-email: asottile@umich.edu
License: MIT
Classifier: Programming Language :: Python :: 3
Classifier: Programming Language :: Python :: 3 :: Only
Classifier: Programming Language :: Python :: Implementation :: CPython
Classifier: Programming Language :: Python :: Implementation :: PyPy
Requires-Python: >=3.9
License-File: LICENSE
Requires-Dist: classify-imports>=4.1
